HSC3D/HSC3D.py
HSC3D/__init__.py
HSC3D-0.2.4.dist-info/License.md
HSC3D-0.2.4.dist-info/METADATA
HSC3D-0.2.4.dist-info/WHEEL
HSC3D-0.2.4.dist-info/top_level.txt
HSC3D-0.2.4.dist-info/RECORD
