Metadata-Version: 2.1
Name: HSC3D
Version: 0.2.4
Summary: HSC3D: a Python package to quantify three-dimensional habitat structural complexity
Home-page: https://github.com/Vicellken/HSC3D
Author: Hu, Jiamian; Gu, Yi-Fei
Author-email: guyf0601@connect.hku.hk
License: Creative Commons Attribution-NonCommercial
Project-URL: Bug Reports, https://github.com/Vicellken/HSC3D/issues
Project-URL: Source, https://github.com/Vicellken/HSC3D
Keywords: 3D point clouds,structural complexity
Requires-Python: >=3.10
License-File: License.md
Requires-Dist: numpy
Requires-Dist: alphashape
Requires-Dist: matplotlib
Requires-Dist: scikit-learn
Requires-Dist: scipy
